README.rst
setup.py
planetpixel/__init__.py
planetpixel/core.py
planetpixel/orders.py
planetpixel/version.py
planetpixel.egg-info/PKG-INFO
planetpixel.egg-info/SOURCES.txt
planetpixel.egg-info/dependency_links.txt
planetpixel.egg-info/top_level.txt