Metadata-Version: 1.1
Name: planetpixel
Version: 0.0.1
Summary: Solving the planet's problems, one pixel at a time.
Home-page: https://barentsen.github.io/planetpixel/
Author: Geert Barentsen
Author-email: hello@geert.io
License: BSD
Platform: UNKNOWN
Classifier: Development Status :: 5 - Production/Stable
Classifier: Intended Audience :: Developers
Classifier: License :: OSI Approved :: BSD License
Classifier: Operating System :: OS Independent
Classifier: Programming Language :: Python
Classifier: Topic :: Documentation
Classifier: Topic :: Software Development :: Documentation
